zeal_feeds/__about__.py
zeal_feeds/__init__.py
zeal_feeds/__main__.py
zeal_feeds/console.py
zeal_feeds/main.py
zeal_feeds/user_contrib.py
zeal_feeds/zeal.py
zeal_feeds-0.3.0.dist-info/METADATA
zeal_feeds-0.3.0.dist-info/WHEEL
zeal_feeds-0.3.0.dist-info/entry_points.txt
zeal_feeds-0.3.0.dist-info/licenses/LICENSE.txt
zeal_feeds-0.3.0.dist-info/RECORD
