Metadata-Version: 2.4
Name: zeal-feeds
Version: 0.3.0
Summary: A command line application for adding user contributed docset feeds to Zeal.
Project-URL: Documentation, https://github.com/smsearcy/zeal-feeds#readme
Project-URL: Issues, https://github.com/smsearcy/zeal-feeds/issues
Project-URL: Source, https://github.com/smsearcy/zeal-feeds
Author-email: Scott Searcy <smsearcy14@outlook.com>
License-Expression: MIT
License-File: LICENSE.txt
Keywords: docsets,zeal
Classifier: Development Status :: 4 - Beta
Classifier: Programming Language :: Python
Classifier: Programming Language :: Python :: 3.9
Classifier: Programming Language :: Python :: 3.10
Classifier: Programming Language :: Python :: 3.11
Classifier: Programming Language :: Python :: Implementation :: CPython
Classifier: Programming Language :: Python :: Implementation :: PyPy
Requires-Python: >=3.9
Requires-Dist: attrs>=21.1.0
Requires-Dist: cattrs
Requires-Dist: platformdirs
Requires-Dist: requests
Requires-Dist: rich
